{
  "schema": "blueprint/autonomous-outcome-snapshot/v1",
  "generated_at": "2026-06-01T12:00:00.000Z",
  "mode": {
    "default_local_only": true,
    "live_read_enabled": false,
    "live_mutation_attempted": false
  },
  "outcomes": [
    {
      "channel_id": "exact_site_hosted_review",
      "budget_line": "Recipient evidence enrichment",
      "source_id": "exact_site_hosted_review_gtm_ledger",
      "proof_level": "missing",
      "proof_status": "missing",
      "can_affect_allocation": false,
      "confidence": 0,
      "score": 0,
      "evidence_refs": [],
      "metrics": {}
    }
  ]
}
